pragzip.pypy37-pp73-darwin.so
pragzip-0.6.0.dist-info/LICENSE-APACHE
pragzip-0.6.0.dist-info/RECORD
pragzip-0.6.0.dist-info/WHEEL
pragzip-0.6.0.dist-info/entry_points.txt
pragzip-0.6.0.dist-info/top_level.txt
pragzip-0.6.0.dist-info/METADATA
pragzip-0.6.0.dist-info/LICENSE-MIT
